connector_factory/.version
connector_factory/__init__.py
connector_factory/decorator.py
connector_factory/factory.py
connector_factory/common/__init__.py
connector_factory/common/common.py
connector_factory/connectors/aws.py
connector_factory/connectors/databricks.py
connector_factory/connectors/db2.py
connector_factory/connectors/dynamodb.py
connector_factory/connectors/mysql.py
connector_factory/connectors/postgreSQL.py
connector_factory/connectors/redshift.py
connector_factory/connectors/s3select.py
connector_factory/connectors/salesforce.py
connector_factory/connectors/snowflake.py
connector_factory/connectors/sqlite3.py
connector_factory/connectors/synapse.py
connector_factory-0.0.5.dist-info/LICENSE
connector_factory-0.0.5.dist-info/METADATA
connector_factory-0.0.5.dist-info/WHEEL
connector_factory-0.0.5.dist-info/top_level.txt
connector_factory-0.0.5.dist-info/RECORD
