Metadata-Version: 2.1
Name: connector-factory
Version: 0.0.5
Summary: Connector Factory;
Home-page: https://github.com/shrivastava-v-ankit/connector-factory
Author: Ankit Shrivastava
License: MIT
Project-URL: Source, https://github.com/shrivastava-v-ankit/connector-factory/
Project-URL: Tracker, https://github.com/shrivastava-v-ankit/connector-factory/issues
Keywords: python,os independent,database,sqlalchemy,sqlite3,sqlite,postgres,mysql,maridb,snowflake,aws,s3select,salesforce
Platform: any
Classifier: Development Status :: 5 - Production/Stable
Classifier: Environment :: Web Environment
Classifier: Intended Audience :: Developers
Classifier: Natural Language :: English
Classifier: License :: OSI Approved :: MIT License
Classifier: Operating System :: OS Independent
Classifier: Programming Language :: Python :: 3.8
Classifier: Programming Language :: Python :: 3.9
Classifier: Programming Language :: Python :: 3.10
Classifier: Programming Language :: Python :: 3.11
Classifier: Topic :: Software Development :: Libraries :: Python Modules
Classifier: Topic :: Software Development :: Version Control :: Git
Requires-Python: >3.8, <3.13
License-File: LICENSE
Requires-Dist: pandas <=2.2.2
Requires-Dist: sqlalchemy <=2.0.31
Requires-Dist: greenlet <=3.0.3
Requires-Dist: numpy <=2.0.0
Requires-Dist: python-dateutil <=2.9.0
Requires-Dist: pytz <=2024.1
Requires-Dist: six <=1.16.0
Requires-Dist: tzdata <=2024.1
Requires-Dist: typing-extensions <=4.12.2
Provides-Extra: all
Requires-Dist: snowflake-connector-python <=3.11.0 ; extra == 'all'
Requires-Dist: snowflake-sqlalchemy <=1.6.1 ; extra == 'all'
Requires-Dist: pyjwt <=2.8.0 ; extra == 'all'
Requires-Dist: asn1crypto <=1.5.1 ; extra == 'all'
Requires-Dist: certifi <=2024.6.2 ; extra == 'all'
Requires-Dist: cffi <=1.16.0 ; extra == 'all'
Requires-Dist: charset-normalizer <=3.3.2 ; extra == 'all'
Requires-Dist: cryptography <=42.0.8 ; extra == 'all'
Requires-Dist: filelock <=3.15.4 ; extra == 'all'
Requires-Dist: idna <=3.7 ; extra == 'all'
Requires-Dist: oscrypto <=1.3.0 ; extra == 'all'
Requires-Dist: packaging <=24.1 ; extra == 'all'
Requires-Dist: platformdirs <=4.2.2 ; extra == 'all'
Requires-Dist: pyOpenSSL <=24.1.0 ; extra == 'all'
Requires-Dist: pycparser <=2.22 ; extra == 'all'
Requires-Dist: pycryptodomex <=3.20.0 ; extra == 'all'
Requires-Dist: requests <=2.32.3 ; extra == 'all'
Requires-Dist: sortedcontainers <=2.4.0 ; extra == 'all'
Requires-Dist: tomlkit <=0.12.5 ; extra == 'all'
Requires-Dist: urllib3 <=1.26.19 ; extra == 'all'
Requires-Dist: boto3 <=1.34.137 ; extra == 'all'
Requires-Dist: botocore <=1.34.137 ; extra == 'all'
Requires-Dist: jmespath <=1.0.1 ; extra == 'all'
Requires-Dist: s3transfer <=0.10.2 ; extra == 'all'
Requires-Dist: psycopg2-binary <=2.9.9 ; extra == 'all'
Requires-Dist: pymysql <=1.1.1 ; extra == 'all'
Requires-Dist: simple-salesforce <=1.12.6 ; extra == 'all'
Requires-Dist: attrs <=23.2.0 ; extra == 'all'
Requires-Dist: isodate <=0.6.1 ; extra == 'all'
Requires-Dist: lxml <=5.2.2 ; extra == 'all'
Requires-Dist: more-itertools <=10.3.0 ; extra == 'all'
Requires-Dist: requests-file <=2.1.0 ; extra == 'all'
Requires-Dist: requests-toolbelt <=1.0.0 ; extra == 'all'
Requires-Dist: zeep <=4.2.1 ; extra == 'all'
Requires-Dist: databricks-sql-connector <=3.2.0 ; extra == 'all'
Requires-Dist: et-xmlfile <=1.1.0 ; extra == 'all'
Requires-Dist: lz4 <=4.3.3 ; extra == 'all'
Requires-Dist: oauthlib <=3.2.2 ; extra == 'all'
Requires-Dist: openpyxl <=3.1.5 ; extra == 'all'
Requires-Dist: pyarrow <=16.1.0 ; extra == 'all'
Requires-Dist: thrift <=0.20.0 ; extra == 'all'
Requires-Dist: pyodbc <=5.1.0 ; extra == 'all'
Requires-Dist: ibm-db-sa <=0.4.0 ; extra == 'all'
Requires-Dist: ibm-db <=3.2.3 ; extra == 'all'
Requires-Dist: PyDynamoDB <=0.6.1 ; extra == 'all'
Requires-Dist: pyparsing <=3.1.2 ; extra == 'all'
Requires-Dist: tenacity <=8.4.2 ; extra == 'all'
Provides-Extra: aws
Requires-Dist: boto3 <=1.34.137 ; extra == 'aws'
Requires-Dist: botocore <=1.34.137 ; extra == 'aws'
Requires-Dist: jmespath <=1.0.1 ; extra == 'aws'
Requires-Dist: s3transfer <=0.10.2 ; extra == 'aws'
Requires-Dist: urllib3 <=1.26.19 ; extra == 'aws'
Provides-Extra: databricks
Requires-Dist: databricks-sql-connector <=3.2.0 ; extra == 'databricks'
Requires-Dist: certifi <=2024.6.2 ; extra == 'databricks'
Requires-Dist: charset-normalizer <=3.3.2 ; extra == 'databricks'
Requires-Dist: et-xmlfile <=1.1.0 ; extra == 'databricks'
Requires-Dist: idna <=3.7 ; extra == 'databricks'
Requires-Dist: lz4 <=4.3.3 ; extra == 'databricks'
Requires-Dist: oauthlib <=3.2.2 ; extra == 'databricks'
Requires-Dist: openpyxl <=3.1.5 ; extra == 'databricks'
Requires-Dist: pyarrow <=16.1.0 ; extra == 'databricks'
Requires-Dist: requests <=2.32.3 ; extra == 'databricks'
Requires-Dist: urllib3 <=1.26.19 ; extra == 'databricks'
Requires-Dist: thrift <=0.20.0 ; extra == 'databricks'
Provides-Extra: db2
Requires-Dist: ibm-db-sa <=0.4.0 ; extra == 'db2'
Requires-Dist: ibm-db <=3.2.3 ; extra == 'db2'
Provides-Extra: dynamodb
Requires-Dist: PyDynamoDB <=0.6.1 ; extra == 'dynamodb'
Requires-Dist: boto3 <=1.34.137 ; extra == 'dynamodb'
Requires-Dist: botocore <=1.34.137 ; extra == 'dynamodb'
Requires-Dist: jmespath <=1.0.1 ; extra == 'dynamodb'
Requires-Dist: pyparsing <=3.1.2 ; extra == 'dynamodb'
Requires-Dist: s3transfer <=0.10.2 ; extra == 'dynamodb'
Requires-Dist: tenacity <=8.4.2 ; extra == 'dynamodb'
Requires-Dist: urllib3 <=1.26.19 ; extra == 'dynamodb'
Provides-Extra: mariadb
Requires-Dist: pymysql <=1.1.1 ; extra == 'mariadb'
Provides-Extra: mysql
Requires-Dist: pymysql <=1.1.1 ; extra == 'mysql'
Provides-Extra: postgres
Requires-Dist: psycopg2-binary <=2.9.9 ; extra == 'postgres'
Provides-Extra: redshift
Requires-Dist: psycopg2-binary <=2.9.9 ; extra == 'redshift'
Provides-Extra: s3select
Requires-Dist: boto3 <=1.34.137 ; extra == 's3select'
Requires-Dist: botocore <=1.34.137 ; extra == 's3select'
Requires-Dist: jmespath <=1.0.1 ; extra == 's3select'
Requires-Dist: s3transfer <=0.10.2 ; extra == 's3select'
Requires-Dist: urllib3 <=1.26.19 ; extra == 's3select'
Provides-Extra: salesforce
Requires-Dist: simple-salesforce <=1.12.6 ; extra == 'salesforce'
Requires-Dist: pyjwt <=2.8.0 ; extra == 'salesforce'
Requires-Dist: attrs <=23.2.0 ; extra == 'salesforce'
Requires-Dist: certifi <=2024.6.2 ; extra == 'salesforce'
Requires-Dist: cffi <=1.16.0 ; extra == 'salesforce'
Requires-Dist: charset-normalizer <=3.3.2 ; extra == 'salesforce'
Requires-Dist: cryptography <=42.0.8 ; extra == 'salesforce'
Requires-Dist: idna <=3.7 ; extra == 'salesforce'
Requires-Dist: isodate <=0.6.1 ; extra == 'salesforce'
Requires-Dist: lxml <=5.2.2 ; extra == 'salesforce'
Requires-Dist: more-itertools <=10.3.0 ; extra == 'salesforce'
Requires-Dist: platformdirs <=4.2.2 ; extra == 'salesforce'
Requires-Dist: pycparser <=2.22 ; extra == 'salesforce'
Requires-Dist: requests <=2.32.3 ; extra == 'salesforce'
Requires-Dist: requests-file <=2.1.0 ; extra == 'salesforce'
Requires-Dist: requests-toolbelt <=1.0.0 ; extra == 'salesforce'
Requires-Dist: urllib3 <=1.26.19 ; extra == 'salesforce'
Requires-Dist: zeep <=4.2.1 ; extra == 'salesforce'
Provides-Extra: snowflake
Requires-Dist: snowflake-connector-python <=3.11.0 ; extra == 'snowflake'
Requires-Dist: snowflake-sqlalchemy <=1.6.1 ; extra == 'snowflake'
Requires-Dist: pyjwt <=2.8.0 ; extra == 'snowflake'
Requires-Dist: asn1crypto <=1.5.1 ; extra == 'snowflake'
Requires-Dist: certifi <=2024.6.2 ; extra == 'snowflake'
Requires-Dist: cffi <=1.16.0 ; extra == 'snowflake'
Requires-Dist: charset-normalizer <=3.3.2 ; extra == 'snowflake'
Requires-Dist: cryptography <=42.0.8 ; extra == 'snowflake'
Requires-Dist: filelock <=3.15.4 ; extra == 'snowflake'
Requires-Dist: idna <=3.7 ; extra == 'snowflake'
Requires-Dist: oscrypto <=1.3.0 ; extra == 'snowflake'
Requires-Dist: packaging <=24.1 ; extra == 'snowflake'
Requires-Dist: platformdirs <=4.2.2 ; extra == 'snowflake'
Requires-Dist: pyOpenSSL <=24.1.0 ; extra == 'snowflake'
Requires-Dist: pycparser <=2.22 ; extra == 'snowflake'
Requires-Dist: pycryptodomex <=3.20.0 ; extra == 'snowflake'
Requires-Dist: requests <=2.32.3 ; extra == 'snowflake'
Requires-Dist: sortedcontainers <=2.4.0 ; extra == 'snowflake'
Requires-Dist: tomlkit <=0.12.5 ; extra == 'snowflake'
Requires-Dist: urllib3 <=1.26.19 ; extra == 'snowflake'
Provides-Extra: synapse
Requires-Dist: pyodbc <=5.1.0 ; extra == 'synapse'
